logmagix/__init__.py
logmagix/font.py
logmagix/logger.py
logmagix/updater.py
logmagix/version.py
logmagix-2.1.3.1.dist-info/licenses/LICENSE
logmagix-2.1.3.1.dist-info/METADATA
logmagix-2.1.3.1.dist-info/WHEEL
logmagix-2.1.3.1.dist-info/top_level.txt
logmagix-2.1.3.1.dist-info/RECORD
