Metadata-Version: 2.4
Name: logmagix
Version: 2.1.3.1
Summary: A custom logger package
Home-page: https://github.com/sexfrance/LogMagix
Author: Sexfrance
Author-email: bwuuuuu@gmail.com
Classifier: Programming Language :: Python :: 3
Classifier: License :: OSI Approved :: MIT License
Classifier: Operating System :: OS Independent
Requires-Python: >=3.6
License-File: LICENSE
Requires-Dist: colorama
Requires-Dist: pystyle
Requires-Dist: packaging
Dynamic: author
Dynamic: author-email
Dynamic: classifier
Dynamic: description
Dynamic: description-content-type
Dynamic: home-page
Dynamic: license-file
Dynamic: requires-dist
Dynamic: requires-python
Dynamic: summary
